<?xml version="1.0" encoding="utf-8"?>
<network>
	<name>yolo_unknown</name>
	<layers>
		<item>
			<type>Input</type>
			<name>Input_0</name>
			<dst>Input_0</dst>
			<input>
				<shape>
					<item>
						<dim>1 3 320 320</dim>
					</item>
				</shape>
			</input>
		</item>
		<item>
			<type>Convolution</type>
			<name>Conv_1</name>
			<src>Input_0</src>
			<dst>Conv_1</dst>
			<weight>
				<item>
					<dim>16 3 3 3</dim>
				</item>
			</weight>
			<convolution>
				<outputNum>16</outputNum>
				<biasTerm>0</biasTerm>
				<kernel>3</kernel>
				<pad>1</pad>
			</convolution>
		</item>
		<item>
			<type>BatchNorm</type>
			<name>BatchNorm_2</name>
			<src>Conv_1</src>
			<dst>Conv_1</dst>
			<weight>
				<item>
					<dim>16</dim>
				</item>
				<item>
					<dim>16</dim>
				</item>
			</weight>
			<batchNorm>
				<eps>1e-06</eps>
				<yoloCompatible>1</yoloCompatible>
			</batchNorm>
		</item>
		<item>
			<type>Scale</type>
			<name>Scale_3</name>
			<src>Conv_1</src>
			<dst>Conv_1</dst>
			<weight>
				<item>
					<dim>16</dim>
				</item>
				<item>
					<dim>16</dim>
				</item>
			</weight>
			<scale>
				<biasTerm>1</biasTerm>
			</scale>
		</item>
		<item>
			<type>ReLU</type>
			<name>ReLU_4</name>
			<src>Conv_1</src>
			<dst>Conv_1</dst>
			<relu>
				<negativeSlope>0.1</negativeSlope>
			</relu>
		</item>
		<item>
			<type>Pooling</type>
			<name>MaxPool_5</name>
			<src>Conv_1</src>
			<dst>MaxPool_5</dst>
			<pooling>
				<method>Max</method>
				<kernel>2</kernel>
				<stride>2</stride>
				<yoloCompatible>1</yoloCompatible>
			</pooling>
		</item>
		<item>
			<type>Convolution</type>
			<name>Conv_6</name>
			<src>MaxPool_5</src>
			<dst>Conv_6</dst>
			<weight>
				<item>
					<dim>32 16 3 3</dim>
				</item>
			</weight>
			<convolution>
				<outputNum>32</outputNum>
				<biasTerm>0</biasTerm>
				<kernel>3</kernel>
				<pad>1</pad>
			</convolution>
		</item>
		<item>
			<type>BatchNorm</type>
			<name>BatchNorm_7</name>
			<src>Conv_6</src>
			<dst>Conv_6</dst>
			<weight>
				<item>
					<dim>32</dim>
				</item>
				<item>
					<dim>32</dim>
				</item>
			</weight>
			<batchNorm>
				<eps>1e-06</eps>
				<yoloCompatible>1</yoloCompatible>
			</batchNorm>
		</item>
		<item>
			<type>Scale</type>
			<name>Scale_8</name>
			<src>Conv_6</src>
			<dst>Conv_6</dst>
			<weight>
				<item>
					<dim>32</dim>
				</item>
				<item>
					<dim>32</dim>
				</item>
			</weight>
			<scale>
				<biasTerm>1</biasTerm>
			</scale>
		</item>
		<item>
			<type>ReLU</type>
			<name>ReLU_9</name>
			<src>Conv_6</src>
			<dst>Conv_6</dst>
			<relu>
				<negativeSlope>0.1</negativeSlope>
			</relu>
		</item>
		<item>
			<type>Pooling</type>
			<name>MaxPool_10</name>
			<src>Conv_6</src>
			<dst>MaxPool_10</dst>
			<pooling>
				<method>Max</method>
				<kernel>2</kernel>
				<stride>2</stride>
				<yoloCompatible>1</yoloCompatible>
			</pooling>
		</item>
		<item>
			<type>Convolution</type>
			<name>Conv_11</name>
			<src>MaxPool_10</src>
			<dst>Conv_11</dst>
			<weight>
				<item>
					<dim>64 32 3 3</dim>
				</item>
			</weight>
			<convolution>
				<outputNum>64</outputNum>
				<biasTerm>0</biasTerm>
				<kernel>3</kernel>
				<pad>1</pad>
			</convolution>
		</item>
		<item>
			<type>BatchNorm</type>
			<name>BatchNorm_12</name>
			<src>Conv_11</src>
			<dst>Conv_11</dst>
			<weight>
				<item>
					<dim>64</dim>
				</item>
				<item>
					<dim>64</dim>
				</item>
			</weight>
			<batchNorm>
				<eps>1e-06</eps>
				<yoloCompatible>1</yoloCompatible>
			</batchNorm>
		</item>
		<item>
			<type>Scale</type>
			<name>Scale_13</name>
			<src>Conv_11</src>
			<dst>Conv_11</dst>
			<weight>
				<item>
					<dim>64</dim>
				</item>
				<item>
					<dim>64</dim>
				</item>
			</weight>
			<scale>
				<biasTerm>1</biasTerm>
			</scale>
		</item>
		<item>
			<type>ReLU</type>
			<name>ReLU_14</name>
			<src>Conv_11</src>
			<dst>Conv_11</dst>
			<relu>
				<negativeSlope>0.1</negativeSlope>
			</relu>
		</item>
		<item>
			<type>Pooling</type>
			<name>MaxPool_15</name>
			<src>Conv_11</src>
			<dst>MaxPool_15</dst>
			<pooling>
				<method>Max</method>
				<kernel>2</kernel>
				<stride>2</stride>
				<yoloCompatible>1</yoloCompatible>
			</pooling>
		</item>
		<item>
			<type>Convolution</type>
			<name>Conv_16</name>
			<src>MaxPool_15</src>
			<dst>Conv_16</dst>
			<weight>
				<item>
					<dim>128 64 3 3</dim>
				</item>
			</weight>
			<convolution>
				<outputNum>128</outputNum>
				<biasTerm>0</biasTerm>
				<kernel>3</kernel>
				<pad>1</pad>
			</convolution>
		</item>
		<item>
			<type>BatchNorm</type>
			<name>BatchNorm_17</name>
			<src>Conv_16</src>
			<dst>Conv_16</dst>
			<weight>
				<item>
					<dim>128</dim>
				</item>
				<item>
					<dim>128</dim>
				</item>
			</weight>
			<batchNorm>
				<eps>1e-06</eps>
				<yoloCompatible>1</yoloCompatible>
			</batchNorm>
		</item>
		<item>
			<type>Scale</type>
			<name>Scale_18</name>
			<src>Conv_16</src>
			<dst>Conv_16</dst>
			<weight>
				<item>
					<dim>128</dim>
				</item>
				<item>
					<dim>128</dim>
				</item>
			</weight>
			<scale>
				<biasTerm>1</biasTerm>
			</scale>
		</item>
		<item>
			<type>ReLU</type>
			<name>ReLU_19</name>
			<src>Conv_16</src>
			<dst>Conv_16</dst>
			<relu>
				<negativeSlope>0.1</negativeSlope>
			</relu>
		</item>
		<item>
			<type>Pooling</type>
			<name>MaxPool_20</name>
			<src>Conv_16</src>
			<dst>MaxPool_20</dst>
			<pooling>
				<method>Max</method>
				<kernel>2</kernel>
				<stride>2</stride>
				<yoloCompatible>1</yoloCompatible>
			</pooling>
		</item>
		<item>
			<type>Convolution</type>
			<name>Conv_21</name>
			<src>MaxPool_20</src>
			<dst>Conv_21</dst>
			<weight>
				<item>
					<dim>256 128 3 3</dim>
				</item>
			</weight>
			<convolution>
				<outputNum>256</outputNum>
				<biasTerm>0</biasTerm>
				<kernel>3</kernel>
				<pad>1</pad>
			</convolution>
		</item>
		<item>
			<type>BatchNorm</type>
			<name>BatchNorm_22</name>
			<src>Conv_21</src>
			<dst>Conv_21</dst>
			<weight>
				<item>
					<dim>256</dim>
				</item>
				<item>
					<dim>256</dim>
				</item>
			</weight>
			<batchNorm>
				<eps>1e-06</eps>
				<yoloCompatible>1</yoloCompatible>
			</batchNorm>
		</item>
		<item>
			<type>Scale</type>
			<name>Scale_23</name>
			<src>Conv_21</src>
			<dst>Conv_21</dst>
			<weight>
				<item>
					<dim>256</dim>
				</item>
				<item>
					<dim>256</dim>
				</item>
			</weight>
			<scale>
				<biasTerm>1</biasTerm>
			</scale>
		</item>
		<item>
			<type>ReLU</type>
			<name>ReLU_24</name>
			<src>Conv_21</src>
			<dst>Conv_21</dst>
			<relu>
				<negativeSlope>0.1</negativeSlope>
			</relu>
		</item>
		<item>
			<type>Convolution</type>
			<name>Conv_25</name>
			<src>Conv_21</src>
			<dst>Conv_25</dst>
			<weight>
				<item>
					<dim>128 256 3 3</dim>
				</item>
			</weight>
			<convolution>
				<outputNum>128</outputNum>
				<biasTerm>0</biasTerm>
				<kernel>3</kernel>
				<pad>1</pad>
			</convolution>
		</item>
		<item>
			<type>BatchNorm</type>
			<name>BatchNorm_26</name>
			<src>Conv_25</src>
			<dst>Conv_25</dst>
			<weight>
				<item>
					<dim>128</dim>
				</item>
				<item>
					<dim>128</dim>
				</item>
			</weight>
			<batchNorm>
				<eps>1e-06</eps>
				<yoloCompatible>1</yoloCompatible>
			</batchNorm>
		</item>
		<item>
			<type>Scale</type>
			<name>Scale_27</name>
			<src>Conv_25</src>
			<dst>Conv_25</dst>
			<weight>
				<item>
					<dim>128</dim>
				</item>
				<item>
					<dim>128</dim>
				</item>
			</weight>
			<scale>
				<biasTerm>1</biasTerm>
			</scale>
		</item>
		<item>
			<type>ReLU</type>
			<name>ReLU_28</name>
			<src>Conv_25</src>
			<dst>Conv_25</dst>
			<relu>
				<negativeSlope>0.1</negativeSlope>
			</relu>
		</item>
		<item>
			<type>Convolution</type>
			<name>Conv_29</name>
			<src>Conv_25</src>
			<dst>Conv_29</dst>
			<weight>
				<item>
					<dim>40 128 1 1</dim>
				</item>
			</weight>
			<convolution>
				<outputNum>40</outputNum>
				<biasTerm>0</biasTerm>
				<kernel>1</kernel>
			</convolution>
		</item>
		<item>
			<type>Bias</type>
			<name>Bias_30</name>
			<src>Conv_29</src>
			<dst>Conv_29</dst>
			<weight>
				<item>
					<dim>40</dim>
				</item>
			</weight>
		</item>
		<item>
			<type>Region</type>
			<name>Region_31</name>
			<src>Conv_29</src>
			<dst>Region_31</dst>
			<region>
				<classes>3</classes>
				<num>5</num>
				<softmax>1</softmax>
				<anchors>0.57273 0.677385 1.87446 2.06253 3.33843 5.47434 7.88282 3.52778 9.77052 9.16828</anchors>
			</region>
		</item>
	</layers>
</network>

